superquantx/__init__.py
superquantx/algorithms.py
superquantx/circuits.py
superquantx/client.py
superquantx/config.py
superquantx/exceptions.py
superquantx/gates.py
superquantx/logging_config.py
superquantx/measurements.py
superquantx/ml.py
superquantx/noise.py
superquantx/version.py
superquantx/algorithms/__init__.py
superquantx/algorithms/base_algorithm.py
superquantx/algorithms/hybrid_classifier.py
superquantx/algorithms/qaoa.py
superquantx/algorithms/quantum_agents.py
superquantx/algorithms/quantum_kmeans.py
superquantx/algorithms/quantum_nn.py
superquantx/algorithms/quantum_pca.py
superquantx/algorithms/quantum_svm.py
superquantx/algorithms/vqe.py
superquantx/backends/__init__.py
superquantx/backends/base_backend.py
superquantx/backends/braket_backend.py
superquantx/backends/cirq_backend.py
superquantx/backends/ocean_backend.py
superquantx/backends/pennylane_backend.py
superquantx/backends/qiskit_backend.py
superquantx/backends/simulator_backend.py
superquantx/backends/tket_backend.py
superquantx/cli/__init__.py
superquantx/cli/commands.py
superquantx/cli/main.py
superquantx/datasets/__init__.py
superquantx/datasets/molecular.py
superquantx/datasets/preprocessing.py
superquantx/datasets/quantum_datasets.py
superquantx/datasets/synthetic.py
superquantx/utils/__init__.py
superquantx/utils/benchmarking.py
superquantx/utils/classical_utils.py
superquantx/utils/feature_mapping.py
superquantx/utils/optimization.py
superquantx/utils/quantum_utils.py
superquantx/utils/visualization.py
superquantx-0.1.3.dist-info/METADATA
superquantx-0.1.3.dist-info/WHEEL
superquantx-0.1.3.dist-info/entry_points.txt
superquantx-0.1.3.dist-info/licenses/LICENSE
superquantx-0.1.3.dist-info/RECORD
