Metadata-Version: 2.4
Name: superquantx
Version: 0.1.3
Summary: Quantum AI Research Platform - Unified API for QuantumAgentic AIsystems research
Project-URL: Homepage, https://github.com/SuperagenticAI/superquantx
Project-URL: Documentation, https://superagenticai.github.io/superquantx
Project-URL: Repository, https://github.com/SuperagenticAI/superquantx
Project-URL: Bug Tracker, https://github.com/SuperagenticAI/superquantx/issues
Project-URL: Source Code, https://github.com/SuperagenticAI/superquantx
Project-URL: Changelog, https://github.com/SuperagenticAI/superquantx/blob/main/CHANGELOG.md
Author-email: Shashi Jagtap <shashi@super-agentic.ai>, Shashi Jagtap <shashikant.jagtap@icloud.com>, SuperXLab Research Team <research@super-agentic.ai>
Maintainer-email: Shashi Jagtap <shashi@super-agentic.ai>, Shashi Jagtap <shashikant.jagtap@icloud.com>, Superagentic AI Research Team <research@super-agentic.ai>
License: Apache-2.0
License-File: LICENSE
Keywords: agentic-ai,braket,cirq,experimental,pennylane,qiskit,quantum-agents,quantum-algorithms,quantum-computing,quantum-machine-learning,research-platform,unified-api
Classifier: Development Status :: 3 - Alpha
Classifier: Intended Audience :: Developers
Classifier: Intended Audience :: Education
Classifier: Intended Audience :: Science/Research
Classifier: License :: OSI Approved :: Apache Software License
Classifier: Operating System :: OS Independent
Classifier: Programming Language :: Python :: 3
Classifier: Programming Language :: Python :: 3.10
Classifier: Programming Language :: Python :: 3.11
Classifier: Programming Language :: Python :: 3.12
Classifier: Topic :: Education
Classifier: Topic :: Scientific/Engineering
Classifier: Topic :: Scientific/Engineering :: Artificial Intelligence
Classifier: Topic :: Scientific/Engineering :: Physics
Classifier: Topic :: Software Development :: Libraries :: Python Modules
Classifier: Typing :: Typed
Requires-Python: >=3.10
Requires-Dist: click>=8.0.0
Requires-Dist: httpx>=0.25.0
Requires-Dist: loguru>=0.7.2
Requires-Dist: matplotlib>=3.8.0
Requires-Dist: networkx>=3.2.0
Requires-Dist: numpy>=1.26.0
Requires-Dist: pydantic>=2.5.0
Requires-Dist: pyyaml>=6.0.0
Requires-Dist: rich>=13.7.0
Requires-Dist: scikit-learn>=1.4.0
Requires-Dist: scipy>=1.12.0
Requires-Dist: typer>=0.12.0
Requires-Dist: typing-extensions>=4.9.0; python_version < '3.11'
Provides-Extra: all-backends
Requires-Dist: amazon-braket-sdk>=1.75.0; extra == 'all-backends'
Requires-Dist: cirq>=1.3.0; extra == 'all-backends'
Requires-Dist: dimod>=0.12.14; extra == 'all-backends'
Requires-Dist: dwave-ocean-sdk>=7.0.0; extra == 'all-backends'
Requires-Dist: pennylane-lightning>=0.35.0; extra == 'all-backends'
Requires-Dist: pennylane>=0.35.0; extra == 'all-backends'
Requires-Dist: pytket-qiskit>=0.50.0; extra == 'all-backends'
Requires-Dist: pytket>=1.25.0; extra == 'all-backends'
Requires-Dist: qiskit-aer>=0.13.0; extra == 'all-backends'
Requires-Dist: qiskit-ibm-runtime>=0.20.0; extra == 'all-backends'
Requires-Dist: qiskit>=1.0.0; extra == 'all-backends'
Provides-Extra: braket
Requires-Dist: amazon-braket-sdk>=1.75.0; extra == 'braket'
Provides-Extra: cirq
Requires-Dist: cirq>=1.3.0; extra == 'cirq'
Provides-Extra: dev
Requires-Dist: black>=24.0.0; extra == 'dev'
Requires-Dist: build>=1.0.0; extra == 'dev'
Requires-Dist: coverage[toml]>=7.4.0; extra == 'dev'
Requires-Dist: mypy>=1.8.0; extra == 'dev'
Requires-Dist: pre-commit>=3.6.0; extra == 'dev'
Requires-Dist: pytest-benchmark>=4.0.0; extra == 'dev'
Requires-Dist: pytest-cov>=4.1.0; extra == 'dev'
Requires-Dist: pytest-mock>=3.12.0; extra == 'dev'
Requires-Dist: pytest-xdist>=3.5.0; extra == 'dev'
Requires-Dist: pytest>=8.0.0; extra == 'dev'
Requires-Dist: ruff>=0.2.0; extra == 'dev'
Requires-Dist: twine>=5.0.0; extra == 'dev'
Provides-Extra: docs
Requires-Dist: mkdocs-gen-files>=0.5.0; extra == 'docs'
Requires-Dist: mkdocs-jupyter>=0.24.0; extra == 'docs'
Requires-Dist: mkdocs-material>=9.5.0; extra == 'docs'
Requires-Dist: mkdocs>=1.5.0; extra == 'docs'
Requires-Dist: mkdocstrings[python]>=0.24.0; extra == 'docs'
Provides-Extra: full-dev
Requires-Dist: amazon-braket-sdk>=1.75.0; extra == 'full-dev'
Requires-Dist: black>=24.0.0; extra == 'full-dev'
Requires-Dist: build>=1.0.0; extra == 'full-dev'
Requires-Dist: cirq>=1.3.0; extra == 'full-dev'
Requires-Dist: coverage[toml]>=7.4.0; extra == 'full-dev'
Requires-Dist: dimod>=0.12.14; extra == 'full-dev'
Requires-Dist: dwave-ocean-sdk>=7.0.0; extra == 'full-dev'
Requires-Dist: mkdocs-gen-files>=0.5.0; extra == 'full-dev'
Requires-Dist: mkdocs-jupyter>=0.24.0; extra == 'full-dev'
Requires-Dist: mkdocs-material>=9.5.0; extra == 'full-dev'
Requires-Dist: mkdocs>=1.5.0; extra == 'full-dev'
Requires-Dist: mkdocstrings[python]>=0.24.0; extra == 'full-dev'
Requires-Dist: mypy>=1.8.0; extra == 'full-dev'
Requires-Dist: pennylane-lightning>=0.35.0; extra == 'full-dev'
Requires-Dist: pennylane>=0.35.0; extra == 'full-dev'
Requires-Dist: pre-commit>=3.6.0; extra == 'full-dev'
Requires-Dist: pytest-benchmark>=4.0.0; extra == 'full-dev'
Requires-Dist: pytest-cov>=4.1.0; extra == 'full-dev'
Requires-Dist: pytest-mock>=3.12.0; extra == 'full-dev'
Requires-Dist: pytest-xdist>=3.5.0; extra == 'full-dev'
Requires-Dist: pytest>=8.0.0; extra == 'full-dev'
Requires-Dist: pytket-qiskit>=0.50.0; extra == 'full-dev'
Requires-Dist: pytket>=1.25.0; extra == 'full-dev'
Requires-Dist: qiskit-aer>=0.13.0; extra == 'full-dev'
Requires-Dist: qiskit-ibm-runtime>=0.20.0; extra == 'full-dev'
Requires-Dist: qiskit>=1.0.0; extra == 'full-dev'
Requires-Dist: ruff>=0.2.0; extra == 'full-dev'
Requires-Dist: twine>=5.0.0; extra == 'full-dev'
Provides-Extra: ocean
Requires-Dist: dimod>=0.12.14; extra == 'ocean'
Requires-Dist: dwave-ocean-sdk>=7.0.0; extra == 'ocean'
Provides-Extra: pennylane
Requires-Dist: pennylane-lightning>=0.35.0; extra == 'pennylane'
Requires-Dist: pennylane>=0.35.0; extra == 'pennylane'
Provides-Extra: qiskit
Requires-Dist: qiskit-aer>=0.13.0; extra == 'qiskit'
Requires-Dist: qiskit-ibm-runtime>=0.20.0; extra == 'qiskit'
Requires-Dist: qiskit>=1.0.0; extra == 'qiskit'
Provides-Extra: tket
Requires-Dist: pytket-qiskit>=0.50.0; extra == 'tket'
Requires-Dist: pytket>=1.25.0; extra == 'tket'
